zc.beforestorage-1.0-py3.9-nspkg.pth
zc/beforestorage/README.rst
zc/beforestorage/__init__.py
zc/beforestorage/component.xml
zc/beforestorage/tests.py
zc.beforestorage-1.0.dist-info/LICENSE.txt
zc.beforestorage-1.0.dist-info/METADATA
zc.beforestorage-1.0.dist-info/WHEEL
zc.beforestorage-1.0.dist-info/namespace_packages.txt
zc.beforestorage-1.0.dist-info/top_level.txt
zc.beforestorage-1.0.dist-info/RECORD
